ouimeaux/__init__.py
ouimeaux/cli.py
ouimeaux/config.py
ouimeaux/discovery.py
ouimeaux/environment.py
ouimeaux/signals.py
ouimeaux/subscribe.py
ouimeaux/utils.py
ouimeaux/device/__init__.py
ouimeaux/device/bridge.py
ouimeaux/device/insight.py
ouimeaux/device/lightswitch.py
ouimeaux/device/maker.py
ouimeaux/device/motion.py
ouimeaux/device/switch.py
ouimeaux/device/api/__init__.py
ouimeaux/device/api/service.py
ouimeaux/device/api/xsd/__init__.py
ouimeaux/device/api/xsd/device.py
ouimeaux/device/api/xsd/device.xsd
ouimeaux/device/api/xsd/service.py
ouimeaux/device/api/xsd/service.xsd
ouimeaux/examples/Randomize.py
ouimeaux/examples/__init__.py
ouimeaux/examples/watch.py
ouimeaux/pysignals/LICENSE.txt
ouimeaux/pysignals/__init__.py
ouimeaux/pysignals/dispatcher.py
ouimeaux/pysignals/inspect.py
ouimeaux/pysignals/license.python.txt
ouimeaux/pysignals/weakref_backports.py
ouimeaux/server/__init__.py
ouimeaux/server/settings.py
ouimeaux/server/static/css/bootstrap-responsive.css
ouimeaux/server/static/css/bootstrap-theme.css
ouimeaux/server/static/css/bootstrap-theme.min.css
ouimeaux/server/static/css/bootstrap.css
ouimeaux/server/static/css/bootstrap.min.css
ouimeaux/server/static/css/main.css
ouimeaux/server/static/fonts/glyphicons-halflings-regular.eot
ouimeaux/server/static/fonts/glyphicons-halflings-regular.svg
ouimeaux/server/static/fonts/glyphicons-halflings-regular.ttf
ouimeaux/server/static/fonts/glyphicons-halflings-regular.woff
ouimeaux/server/static/img/favicon.ico
ouimeaux/server/static/js/app.js
ouimeaux/server/static/js/bootstrap.js
ouimeaux/server/static/js/bootstrap.min.js
ouimeaux/server/static/js/controllers.js
ouimeaux/server/static/js/directives.js
ouimeaux/server/static/js/filters.js
ouimeaux/server/static/js/services.js
ouimeaux/server/static/js/socket.js
ouimeaux/server/static/lib/angular/angular-resource.js
ouimeaux/server/static/lib/angular/angular-resource.min.js
ouimeaux-0.8.2.dist-info/DESCRIPTION.rst
ouimeaux-0.8.2.dist-info/METADATA
ouimeaux-0.8.2.dist-info/RECORD
ouimeaux-0.8.2.dist-info/WHEEL
ouimeaux-0.8.2.dist-info/entry_points.txt
ouimeaux-0.8.2.dist-info/metadata.json
ouimeaux-0.8.2.dist-info/top_level.txt
