Metadata-Version: 2.0
Name: ouimeaux
Version: 0.8.2
Summary: Open source control for Belkin WeMo devices
Home-page: https://github.com/iancmcc/ouimeaux
Author: Ian McCracken
Author-email: ian.mccracken@gmail.com
License: BSD
Keywords: ouimeaux
Platform: UNKNOWN
Classifier: Development Status :: 2 - Pre-Alpha
Classifier: Topic :: Home Automation
Classifier: Intended Audience :: Developers
Classifier: License :: OSI Approved :: BSD License
Classifier: Natural Language :: English
Classifier: Programming Language :: Python :: 2
Classifier: Programming Language :: Python :: 2.6
Classifier: Programming Language :: Python :: 2.7
Classifier: Programming Language :: Python :: 3
Classifier: Programming Language :: Python :: 3.3
Classifier: Programming Language :: Python :: 3.4
Classifier: Programming Language :: Python :: 3.5
Provides-Extra: server
Requires-Dist: gevent (>=1.3.0)
Requires-Dist: requests (>=2.3.0)
Requires-Dist: pyyaml
Requires-Dist: six
Requires-Dist: future
Provides-Extra: server
Requires-Dist: flask-restful; extra == 'server'
Requires-Dist: flask-basicauth; extra == 'server'
Requires-Dist: gevent-socketio; extra == 'server'
Requires-Dist: flask-cors; extra == 'server'
